kvs3/__init__.py
kvs3/commands.py
kvs3/main.py
kvs3-0.0.5.dist-info/LICENSE
kvs3-0.0.5.dist-info/METADATA
kvs3-0.0.5.dist-info/WHEEL
kvs3-0.0.5.dist-info/entry_points.txt
kvs3-0.0.5.dist-info/top_level.txt
kvs3-0.0.5.dist-info/RECORD
