Metadata-Version: 2.1
Name: kvs3
Version: 0.0.5
Summary: Command-line tool to interact with s3 bucket as a key/value store
Home-page: https://github.com/ncheneweth/kvs3
Author: Nic Cheneweth
Author-email: nic.cheneweth@thoughtworks.com
License: UNKNOWN
Platform: UNKNOWN
Classifier: Programming Language :: Python :: 3
Classifier: License :: OSI Approved :: MIT License
Classifier: Operating System :: POSIX :: Linux
Requires-Dist: invoke
Requires-Dist: boto3
Requires-Dist: pyyaml
Requires-Dist: requests
